SCOS/SCOS.py
SCOS/__init__.py
SCOSpy-0.4.5.dist-info/LICENSE
SCOSpy-0.4.5.dist-info/METADATA
SCOSpy-0.4.5.dist-info/WHEEL
SCOSpy-0.4.5.dist-info/top_level.txt
SCOSpy-0.4.5.dist-info/RECORD
