Metadata-Version: 2.1
Name: SCOSpy
Version: 0.4.5
Summary: Python library to read the SCOS-2000 header
Author-email: Romolo Politi <romolo.politi@inaf.it>
License: GNU GPL ver3
Project-URL: Repository, https://github.com/RomoloPoliti-INAF/SCOSpy
Classifier: Programming Language :: Python :: 3.9
Classifier: License :: OSI Approved :: GNU General Public License v3 (GPLv3)
Classifier: Operating System :: OS Independent
Requires-Python: >=3.11
License-File: LICENSE
Requires-Dist: bitstring
Provides-Extra: docs
Requires-Dist: sphinx ; extra == 'docs'
